LICENSE
MANIFEST.in
README.md
setup.py
bin/storytracker-archive
bin/storytracker-get
bin/storytracker-links2csv
storytracker/__init__.py
storytracker/analysis.py
storytracker/archive.py
storytracker/exceptions.py
storytracker/files.py
storytracker/get.py
storytracker/images2gif.py
storytracker/pastpages.py
storytracker/toolbox.py
storytracker/waybackmachine.py
storytracker.egg-info/PKG-INFO
storytracker.egg-info/SOURCES.txt
storytracker.egg-info/dependency_links.txt
storytracker.egg-info/not-zip-safe
storytracker.egg-info/requires.txt
storytracker.egg-info/top_level.txt
storytracker/fonts/OpenSans-Regular.ttf
storytracker/templates/archivedurl.html
storytracker/templates/archivedurlset.html
storytracker/templates/head.html
storytracker/templates/header.html