Metadata-Version: 1.0
Name: storytracker
Version: 1.0.1
Summary: Tools for tracking stories for news homepages
Home-page: https://github.com/pastpages/storytracker
Author: Ben Welsh
Author-email: ben.welsh@gmail.com
License: MIT
Platform: UNKNOWN
